steep/__init__.py
steep/account.py
steep/aes.py
steep/amount.py
steep/block.py
steep/blockchain.py
steep/blog.py
steep/commit.py
steep/consts.py
steep/converter.py
steep/dex.py
steep/instance.py
steep/post.py
steep/profile.py
steep/steem.py
steep/steemd.py
steep/transactionbuilder.py
steep/utils.py
steep/wallet.py
steep/witness.py
steep_steem-0.1.2.dist-info/METADATA
steep_steem-0.1.2.dist-info/RECORD
steep_steem-0.1.2.dist-info/WHEEL
steep_steem-0.1.2.dist-info/top_level.txt
steepbase/__init__.py
steepbase/account.py
steepbase/base58.py
steepbase/base_client.py
steepbase/bip38.py
steepbase/chains.py
steepbase/connector.py
steepbase/dictionary.py
steepbase/exceptions.py
steepbase/http_client.py
steepbase/memo.py
steepbase/operationids.py
steepbase/operations.py
steepbase/storage.py
steepbase/transactions.py
steepbase/types.py
steepbase/ws_client.py
